{
	"start":	{
		"connected":	[{
				"socket":	5,
				"local_host":	"10.0.1.1",
				"local_port":	49552,
				"remote_host":	"10.0.0.1",
				"remote_port":	5201
			}],
		"version":	"iperf 3.9+",
		"system_info":	"Linux han-3 5.10.0 #9 SMP PREEMPT Tue Feb 23 15:01:43 PST 2021 x86_64",
		"timestamp":	{
			"time":	"Sat, 02 Mar 2024 23:56:29 GMT",
			"timesecs":	1709423789
		},
		"connecting_to":	{
			"host":	"10.0.0.1",
			"port":	5201
		},
		"cookie":	"frlyum5haigzuvdulf3x7i6p3tsjzixrdnqk",
		"tcp_mss_default":	1448,
		"target_bitrate":	9000000000,
		"sock_bufsize":	0,
		"sndbuf_actual":	16384,
		"rcvbuf_actual":	131072,
		"test_start":	{
			"protocol":	"TCP",
			"num_streams":	1,
			"blksize":	131072,
			"omit":	0,
			"duration":	40,
			"bytes":	0,
			"blocks":	0,
			"reverse":	0,
			"tos":	0
		}
	},
	"intervals":	[{
			"streams":	[{
					"socket":	5,
					"start":	0,
					"end":	40.000109,
					"seconds":	40.0001106262207,
					"bytes":	43284824064,
					"bits_per_second":	8656940870.6837158,
					"retransmits":	0,
					"snd_cwnd":	4187616,
					"rtt":	1118,
					"rttvar":	47,
					"pmtu":	9000,
					"omitted":	false,
					"sender":	true
				}],
			"sum":	{
				"start":	0,
				"end":	40.000109,
				"seconds":	40.0001106262207,
				"bytes":	43284824064,
				"bits_per_second":	8656940870.6837158,
				"retransmits":	0,
				"omitted":	false,
				"sender":	true
			}
		}],
	"end":	{
		"streams":	[{
				"sender":	{
					"socket":	5,
					"start":	0,
					"end":	40.000109,
					"seconds":	40.000109,
					"bytes":	43284824064,
					"bits_per_second":	8656941222.63517,
					"retransmits":	0,
					"max_snd_cwnd":	4187616,
					"max_rtt":	1118,
					"min_rtt":	1118,
					"mean_rtt":	1118,
					"sender":	true
				},
				"receiver":	{
					"socket":	5,
					"start":	0,
					"end":	40.00044,
					"seconds":	40.000109,
					"bytes":	43282565344,
					"bits_per_second":	8656417848.20367,
					"sender":	true
				}
			}],
		"sum_sent":	{
			"start":	0,
			"end":	40.000109,
			"seconds":	40.000109,
			"bytes":	43284824064,
			"bits_per_second":	8656941222.63517,
			"retransmits":	0,
			"sender":	true
		},
		"sum_received":	{
			"start":	0,
			"end":	40.00044,
			"seconds":	40.00044,
			"bytes":	43282565344,
			"bits_per_second":	8656417848.20367,
			"sender":	true
		},
		"cpu_utilization_percent":	{
			"host_total":	91.7341050823104,
			"host_user":	2.3390230646493593,
			"host_system":	89.395087017373669,
			"remote_total":	45.8051969377167,
			"remote_user":	3.3335895384464886,
			"remote_system":	42.471602408261518
		},
		"sender_tcp_congestion":	"cubic",
		"receiver_tcp_congestion":	"reno"
	}
}
