{
	"start":	{
		"connected":	[{
				"socket":	5,
				"local_host":	"10.0.1.1",
				"local_port":	45646,
				"remote_host":	"10.0.0.1",
				"remote_port":	5201
			}],
		"version":	"iperf 3.9+",
		"system_info":	"Linux han-3 5.10.0 #9 SMP PREEMPT Tue Feb 23 15:01:43 PST 2021 x86_64",
		"timestamp":	{
			"time":	"Sat, 02 Mar 2024 10:15:02 GMT",
			"timesecs":	1709374502
		},
		"connecting_to":	{
			"host":	"10.0.0.1",
			"port":	5201
		},
		"cookie":	"aiu6hc4iicahrkpung3xphx6dq5w4kvcyhds",
		"tcp_mss_default":	1448,
		"target_bitrate":	10000000000,
		"sock_bufsize":	0,
		"sndbuf_actual":	16384,
		"rcvbuf_actual":	131072,
		"test_start":	{
			"protocol":	"TCP",
			"num_streams":	1,
			"blksize":	131072,
			"omit":	0,
			"duration":	40,
			"bytes":	0,
			"blocks":	0,
			"reverse":	0,
			"tos":	0
		}
	},
	"intervals":	[{
			"streams":	[{
					"socket":	5,
					"start":	0,
					"end":	40.000295,
					"seconds":	40.000293731689453,
					"bytes":	47048032256,
					"bits_per_second":	9409537354.2174,
					"retransmits":	0,
					"snd_cwnd":	4113768,
					"rtt":	1122,
					"rttvar":	45,
					"pmtu":	9000,
					"omitted":	false,
					"sender":	true
				}],
			"sum":	{
				"start":	0,
				"end":	40.000295,
				"seconds":	40.000293731689453,
				"bytes":	47048032256,
				"bits_per_second":	9409537354.2174,
				"retransmits":	0,
				"omitted":	false,
				"sender":	true
			}
		}],
	"end":	{
		"streams":	[{
				"sender":	{
					"socket":	5,
					"start":	0,
					"end":	40.000295,
					"seconds":	40.000295,
					"bytes":	47048032256,
					"bits_per_second":	9409537055.86421,
					"retransmits":	0,
					"max_snd_cwnd":	4113768,
					"max_rtt":	1122,
					"min_rtt":	1122,
					"mean_rtt":	1122,
					"sender":	true
				},
				"receiver":	{
					"socket":	5,
					"start":	0,
					"end":	40.000828,
					"seconds":	40.000295,
					"bytes":	47046038808,
					"bits_per_second":	9409012995.031004,
					"sender":	true
				}
			}],
		"sum_sent":	{
			"start":	0,
			"end":	40.000295,
			"seconds":	40.000295,
			"bytes":	47048032256,
			"bits_per_second":	9409537055.86421,
			"retransmits":	0,
			"sender":	true
		},
		"sum_received":	{
			"start":	0,
			"end":	40.000828,
			"seconds":	40.000828,
			"bytes":	47046038808,
			"bits_per_second":	9409012995.031004,
			"sender":	true
		},
		"cpu_utilization_percent":	{
			"host_total":	41.363872941178826,
			"host_user":	1.9512572539651509,
			"host_system":	39.412613187354914,
			"remote_total":	48.204840305001554,
			"remote_user":	0.48717710615170956,
			"remote_system":	47.717660701939835
		},
		"sender_tcp_congestion":	"cubic",
		"receiver_tcp_congestion":	"reno"
	}
}
