{
	"start":	{
		"connected":	[{
				"socket":	5,
				"local_host":	"10.0.1.1",
				"local_port":	42332,
				"remote_host":	"10.0.0.1",
				"remote_port":	5201
			}],
		"version":	"iperf 3.9+",
		"system_info":	"Linux han-3 5.10.0 #9 SMP PREEMPT Tue Feb 23 15:01:43 PST 2021 x86_64",
		"timestamp":	{
			"time":	"Fri, 01 Mar 2024 22:44:59 GMT",
			"timesecs":	1709333099
		},
		"connecting_to":	{
			"host":	"10.0.0.1",
			"port":	5201
		},
		"cookie":	"xm2mamxnn6tur6ldeuzkbbe5apqnjii2sptm",
		"tcp_mss_default":	1448,
		"target_bitrate":	2000000000,
		"sock_bufsize":	0,
		"sndbuf_actual":	16384,
		"rcvbuf_actual":	131072,
		"test_start":	{
			"protocol":	"TCP",
			"num_streams":	1,
			"blksize":	131072,
			"omit":	0,
			"duration":	80,
			"bytes":	0,
			"blocks":	0,
			"reverse":	0,
			"tos":	0
		}
	},
	"intervals":	[{
			"streams":	[{
					"socket":	5,
					"start":	0,
					"end":	60.000064,
					"seconds":	60.000064849853516,
					"bytes":	14999879680,
					"bits_per_second":	1999981795.6912253,
					"retransmits":	0,
					"snd_cwnd":	431504,
					"rtt":	269,
					"rttvar":	31,
					"pmtu":	9000,
					"omitted":	false,
					"sender":	true
				}],
			"sum":	{
				"start":	0,
				"end":	60.000064,
				"seconds":	60.000064849853516,
				"bytes":	14999879680,
				"bits_per_second":	1999981795.6912253,
				"retransmits":	0,
				"omitted":	false,
				"sender":	true
			}
		}, {
			"streams":	[{
					"socket":	5,
					"start":	60.000064,
					"end":	80.000114,
					"seconds":	20.000049591064453,
					"bytes":	5000003584,
					"bits_per_second":	1999996474.5022964,
					"retransmits":	0,
					"snd_cwnd":	431504,
					"rtt":	293,
					"rttvar":	43,
					"pmtu":	9000,
					"omitted":	false,
					"sender":	true
				}],
			"sum":	{
				"start":	60.000064,
				"end":	80.000114,
				"seconds":	20.000049591064453,
				"bytes":	5000003584,
				"bits_per_second":	1999996474.5022964,
				"retransmits":	0,
				"omitted":	false,
				"sender":	true
			}
		}],
	"end":	{
		"streams":	[{
				"sender":	{
					"socket":	5,
					"start":	0,
					"end":	80.000114,
					"seconds":	80.000114,
					"bytes":	19999883264,
					"bits_per_second":	1999985476.4206963,
					"retransmits":	0,
					"max_snd_cwnd":	431504,
					"max_rtt":	293,
					"min_rtt":	269,
					"mean_rtt":	281,
					"sender":	true
				},
				"receiver":	{
					"socket":	5,
					"start":	0,
					"end":	79.999925,
					"seconds":	80.000114,
					"bytes":	19999883264,
					"bits_per_second":	1999990201.3908136,
					"sender":	true
				}
			}],
		"sum_sent":	{
			"start":	0,
			"end":	80.000114,
			"seconds":	80.000114,
			"bytes":	19999883264,
			"bits_per_second":	1999985476.4206963,
			"retransmits":	0,
			"sender":	true
		},
		"sum_received":	{
			"start":	0,
			"end":	79.999925,
			"seconds":	79.999925,
			"bytes":	19999883264,
			"bits_per_second":	1999990201.3908136,
			"sender":	true
		},
		"cpu_utilization_percent":	{
			"host_total":	14.193292701516189,
			"host_user":	0.77583082317197283,
			"host_system":	13.417463128305265,
			"remote_total":	21.602714602323314,
			"remote_user":	0.39346244515943074,
			"remote_system":	21.209252157163881
		},
		"sender_tcp_congestion":	"cubic",
		"receiver_tcp_congestion":	"reno"
	}
}
