{
	"start":	{
		"connected":	[{
				"socket":	5,
				"local_host":	"10.0.1.1",
				"local_port":	32908,
				"remote_host":	"10.0.0.1",
				"remote_port":	5201
			}],
		"version":	"iperf 3.9+",
		"system_info":	"Linux han-3 5.10.0 #9 SMP PREEMPT Tue Feb 23 15:01:43 PST 2021 x86_64",
		"timestamp":	{
			"time":	"Thu, 25 May 2023 07:14:53 GMT",
			"timesecs":	1684998893
		},
		"connecting_to":	{
			"host":	"10.0.0.1",
			"port":	5201
		},
		"cookie":	"rtqjtnndmzv4sctxofp54cqbenrixvydezae",
		"tcp_mss_default":	8948,
		"target_bitrate":	5000000000,
		"sock_bufsize":	0,
		"sndbuf_actual":	16384,
		"rcvbuf_actual":	131072,
		"test_start":	{
			"protocol":	"TCP",
			"num_streams":	1,
			"blksize":	131072,
			"omit":	0,
			"duration":	20,
			"bytes":	0,
			"blocks":	0,
			"reverse":	0,
			"tos":	0
		}
	},
	"intervals":	[{
			"streams":	[{
					"socket":	5,
					"start":	0,
					"end":	20.000084,
					"seconds":	20.000083923339844,
					"bytes":	12499550208,
					"bits_per_second":	4999799103.2080355,
					"retransmits":	13,
					"snd_cwnd":	715840,
					"rtt":	571,
					"rttvar":	33,
					"pmtu":	9000,
					"omitted":	false,
					"sender":	true
				}],
			"sum":	{
				"start":	0,
				"end":	20.000084,
				"seconds":	20.000083923339844,
				"bytes":	12499550208,
				"bits_per_second":	4999799103.2080355,
				"retransmits":	13,
				"omitted":	false,
				"sender":	true
			}
		}],
	"end":	{
		"streams":	[{
				"sender":	{
					"socket":	5,
					"start":	0,
					"end":	20.000084,
					"seconds":	20.000084,
					"bytes":	12499550208,
					"bits_per_second":	4999799084.0438471,
					"retransmits":	13,
					"max_snd_cwnd":	715840,
					"max_rtt":	571,
					"min_rtt":	571,
					"mean_rtt":	571,
					"sender":	true
				},
				"receiver":	{
					"socket":	5,
					"start":	0,
					"end":	20.000274,
					"seconds":	20.000084,
					"bytes":	12499550208,
					"bits_per_second":	4999751586.6032629,
					"sender":	true
				}
			}],
		"sum_sent":	{
			"start":	0,
			"end":	20.000084,
			"seconds":	20.000084,
			"bytes":	12499550208,
			"bits_per_second":	4999799084.0438471,
			"retransmits":	13,
			"sender":	true
		},
		"sum_received":	{
			"start":	0,
			"end":	20.000274,
			"seconds":	20.000274,
			"bytes":	12499550208,
			"bits_per_second":	4999751586.6032629,
			"sender":	true
		},
		"cpu_utilization_percent":	{
			"host_total":	14.452783201352732,
			"host_user":	0,
			"host_system":	14.452783201352732,
			"remote_total":	44.574327391741477,
			"remote_user":	0.635588791265187,
			"remote_system":	43.9387386004763
		},
		"sender_tcp_congestion":	"cubic",
		"receiver_tcp_congestion":	"reno"
	}
}
