{
	"start":	{
		"connected":	[{
				"socket":	5,
				"local_host":	"10.0.1.1",
				"local_port":	47086,
				"remote_host":	"10.0.0.1",
				"remote_port":	5201
			}],
		"version":	"iperf 3.9+",
		"system_info":	"Linux han-3 5.10.0 #9 SMP PREEMPT Tue Feb 23 15:01:43 PST 2021 x86_64",
		"timestamp":	{
			"time":	"Thu, 11 May 2023 22:31:32 GMT",
			"timesecs":	1683844292
		},
		"connecting_to":	{
			"host":	"10.0.0.1",
			"port":	5201
		},
		"cookie":	"dl72ngzktzg3zvahmyisxow7deiqhrhsjcbx",
		"tcp_mss_default":	8948,
		"sock_bufsize":	0,
		"sndbuf_actual":	16384,
		"rcvbuf_actual":	131072,
		"test_start":	{
			"protocol":	"TCP",
			"num_streams":	1,
			"blksize":	131072,
			"omit":	0,
			"duration":	0,
			"bytes":	53687091200,
			"blocks":	0,
			"reverse":	0,
			"tos":	0
		}
	},
	"intervals":	[{
			"streams":	[{
					"socket":	5,
					"start":	0,
					"end":	43.388556,
					"seconds":	43.388557434082031,
					"bytes":	53687091200,
					"bits_per_second":	9898847876.0215054,
					"retransmits":	2207,
					"snd_cwnd":	1539056,
					"rtt":	1199,
					"rttvar":	14,
					"pmtu":	9000,
					"omitted":	false,
					"sender":	true
				}],
			"sum":	{
				"start":	0,
				"end":	43.388556,
				"seconds":	43.388557434082031,
				"bytes":	53687091200,
				"bits_per_second":	9898847876.0215054,
				"retransmits":	2207,
				"omitted":	false,
				"sender":	true
			}
		}],
	"end":	{
		"streams":	[{
				"sender":	{
					"socket":	5,
					"start":	0,
					"end":	43.388556,
					"seconds":	43.388556,
					"bytes":	53687091200,
					"bits_per_second":	9898848203.19902,
					"retransmits":	2207,
					"max_snd_cwnd":	1539056,
					"max_rtt":	1199,
					"min_rtt":	1199,
					"mean_rtt":	1199,
					"sender":	true
				},
				"receiver":	{
					"socket":	5,
					"start":	0,
					"end":	43.389885,
					"seconds":	43.388556,
					"bytes":	53685323184,
					"bits_per_second":	9898219031.2788334,
					"sender":	true
				}
			}],
		"sum_sent":	{
			"start":	0,
			"end":	43.388556,
			"seconds":	43.388556,
			"bytes":	53687091200,
			"bits_per_second":	9898848203.19902,
			"retransmits":	2207,
			"sender":	true
		},
		"sum_received":	{
			"start":	0,
			"end":	43.389885,
			"seconds":	43.389885,
			"bytes":	53685323184,
			"bits_per_second":	9898219031.2788334,
			"sender":	true
		},
		"cpu_utilization_percent":	{
			"host_total":	26.596475841140581,
			"host_user":	1.2148603572943546,
			"host_system":	25.381615483846225,
			"remote_total":	50.833718184079167,
			"remote_user":	3.2809222566496521,
			"remote_system":	47.552795927429514
		},
		"sender_tcp_congestion":	"reno",
		"receiver_tcp_congestion":	"cubic"
	}
}
